mini_vss/__init__.py
mini_vss/client.py
mini_vss/command_line.py
mini_vss/configs.py
mini_vss/maintainer.py
mini_vss/platform.py
mini_vss/signature.py
mini_vss/version.py
mini_vss-0.0.5.dist-info/LICENSE
mini_vss-0.0.5.dist-info/METADATA
mini_vss-0.0.5.dist-info/WHEEL
mini_vss-0.0.5.dist-info/entry_points.txt
mini_vss-0.0.5.dist-info/top_level.txt
mini_vss-0.0.5.dist-info/RECORD
