Metadata-Version: 2.1
Name: mini-vss
Version: 0.0.5
Summary: Version Sharing System
Home-page: https://github.com/Atominick/MiniVSS
Author: Atominick
Author-email: atominick@ukr.net
License: UNKNOWN
Platform: UNKNOWN
Classifier: Topic :: Communications :: File Sharing
Classifier: License :: OSI Approved :: MIT License
Classifier: Development Status :: 2 - Pre-Alpha
Classifier: Programming Language :: Python
Requires-Python: >=3.6
License-File: LICENSE
Requires-Dist: semantic-version
Requires-Dist: pycryptodome
Requires-Dist: requests
